grafliq/__init__.py
grafliq/builder.py
grafliq/query.py
grafliq-0.1.0.dist-info/LICENSE
grafliq-0.1.0.dist-info/METADATA
grafliq-0.1.0.dist-info/WHEEL
grafliq-0.1.0.dist-info/top_level.txt
grafliq-0.1.0.dist-info/RECORD
