Metadata-Version: 2.1
Name: grafliq
Version: 0.1.0
Summary: A simple and pythonic way to query GraphQL endpoints without having to do any string manipulation.
Home-page: https://github.com/mononobi/grafliq
Author: mono
Author-email: mononobi@gmail.com
Maintainer: mono
Maintainer-email: mononobi@gmail.com
License: BSD-3-Clause
Project-URL: Code, https://github.com/mononobi/grafliq
Project-URL: Issue tracker, https://github.com/mononobi/grafliq/issues
Keywords: graphql python grafliq graphql-query pythonic graphql-client graphql-tool pythonic-graphql-tool graphql-for-humans pythonic-graphql graphql-query-builder graphql-queries graphql-query-generator
Classifier: Development Status :: 5 - Production/Stable
Classifier: Environment :: Web Environment
Classifier: Intended Audience :: Developers
Classifier: License :: OSI Approved :: BSD License
Classifier: Operating System :: OS Independent
Classifier: Programming Language :: Python
Classifier: Programming Language :: Python :: 3.6
Classifier: Programming Language :: Python :: 3.7
Classifier: Programming Language :: Python :: 3.8
Classifier: Programming Language :: Python :: 3.9
Classifier: Programming Language :: Python :: 3.10
Classifier: Programming Language :: Python :: 3.11
Classifier: Programming Language :: Python :: 3.12
Classifier: Programming Language :: Python :: Implementation :: CPython
Classifier: Topic :: Internet :: WWW/HTTP :: Dynamic Content
Classifier: Topic :: Software Development :: Libraries :: Python Modules
Requires-Python: >=3.6
License-File: LICENSE
Requires-Dist: requests ==2.32.3
Provides-Extra: tests
Requires-Dist: requests ==2.32.3 ; extra == 'tests'
Requires-Dist: pytest ==8.3.2 ; extra == 'tests'
Requires-Dist: pytest-cov ==5.0.0 ; extra == 'tests'
Requires-Dist: pygments ==2.18.0 ; extra == 'tests'
